pysunspec_read/__init__.py
pysunspec_read/clean_dict.py
pysunspec_read/connect_options.py
pysunspec_read/dates.py
pysunspec_read/device_reader.py
pysunspec_read/files.py
pysunspec_read/init_logging.py
pysunspec_read/output_filter_predicates.py
pysunspec_read/output_options.py
pysunspec_read/read_to_output.py
pysunspec_read/schema.py
pysunspec_read/demo/__init__.py
pysunspec_read/demo/demo_ip.py
pysunspec_read/demo/demo_ip_file.py
pysunspec_read/demo/read_sample.py
pysunspec_read-0.20.7.dist-info/METADATA
pysunspec_read-0.20.7.dist-info/WHEEL
pysunspec_read-0.20.7.dist-info/top_level.txt
pysunspec_read-0.20.7.dist-info/RECORD
