Metadata-Version: 2.1
Name: pysunspec-read
Version: 0.20.7
Summary: read from solar inverters that implement the SunSpec interface, to simpler datastructure
Home-page: https://bitbucket.org/clockworkcodeteam/pysunspec-read/src/master/
Author: dilbertau99
Author-email: dilbertau99@gmail.com
License: GNU General Public License V3 or later
Keywords: solar monitoring inverter communications reader
Platform: UNKNOWN
Classifier: Programming Language :: Python :: 3
Classifier: License :: OSI Approved :: GNU General Public License v3 or later (GPLv3+)
Classifier: Operating System :: OS Independent
Classifier: Development Status :: 1 - Planning
Classifier: Intended Audience :: End Users/Desktop
Classifier: Natural Language :: English
Classifier: Topic :: Utilities
Classifier: Topic :: Communications
Requires-Dist: pysunspec2
Requires-Dist: pyserial
Requires-Dist: pyyaml
